LICENSE
syntags/__init__.py
syntags/ext.py
syntags/html.py
syntags/lib/components.py
syntags/lib/elements.py
syntags/lib/syntax.py
syntags/lib/utils.py
syntags/README.md
syntags/rss.py
syntags/sitemap.py
syntags/svg.py
syntags/xml.py
syntags-0.2.0.dist-info/LICENSE
syntags-0.2.0.dist-info/WHEEL
syntags-0.2.0.dist-info/METADATA
syntags-0.2.0.dist-info/RECORD
