Metadata-Version: 2.1
Name: syntags
Version: 0.2.0
Summary: A beautiful python syntax to generate HTML.
Home-page: https://github.com/SeparateRecords/Syntags
License: ISC
Keywords: html,dsl,markup,syntax,tags
Author: SeparateRecords
Author-email: me@rob.ac
Requires-Python: >=3.8,<4.0
Classifier: Development Status :: 3 - Alpha
Classifier: Intended Audience :: Developers
Classifier: License :: OSI Approved
Classifier: License :: OSI Approved :: ISC License (ISCL)
Classifier: Programming Language :: Python :: 3
Classifier: Programming Language :: Python :: 3.8
Classifier: Topic :: Text Processing :: Markup :: HTML
Provides-Extra: markdown
Requires-Dist: markdown2 (>=2.3.8,<3.0.0); extra == "markdown"
Requires-Dist: pygments (>=2.5.2,<3.0.0); extra == "markdown"
Project-URL: Repository, https://github.com/SeparateRecords/Syntags
